[
  {
    "id": "管理学_1780641191316_0_89rp",
    "module": "管理学",
    "stem": "在某次A320飞机定检中，班组长张工发现新员工小刘在更换刹车风扇时未按工单要求在螺栓上涂抹防咬剂，张工立即叫停并纠正。事后，张工在班组早会上以此为例进行讲评。从管理职能看，张工的讲评主要体现了：",
    "options": [
      {
        "label": "A",
        "text": "计划职能，为后续工作制定标准流程"
      },
      {
        "label": "B",
        "text": "组织职能，重新调整班组人员分工"
      },
      {
        "label": "C",
        "text": "控制职能，通过纠偏反馈来确保工作标准被执行"
      },
      {
        "label": "D",
        "text": "领导职能，激励员工士气以确保生产安全"
      }
    ],
    "answer": "C",
    "explanation": "管理控制职能强调对实际工作进行衡量和纠偏，早会讲评是反馈环节，属于典型的现场控制。考点速记：控制职能三步骤——确立标准、衡量绩效、纠正偏差。"
  },
  {
    "id": "管理学_1780641191317_1_oqir",
    "module": "管理学",
    "stem": "某维修基地承接一架B737NG的紧急AOG排故任务，发动机引气故障导致航班延误。项目负责人老李抽调了航线和定检的骨干组成专项小组，并授权小组负责人直接调配基地航材与特种车辆。这一授权行为最直接的目的是：",
    "options": [
      {
        "label": "A",
        "text": "增加项目复杂度以锻炼队伍"
      },
      {
        "label": "B",
        "text": "打破部门墙，提高跨单元应急协作效率"
      },
      {
        "label": "C",
        "text": "削减管理层级以降低人力成本"
      },
      {
        "label": "D",
        "text": "分散责任以减少项目负责人的安全压力"
      }
    ],
    "answer": "B",
    "explanation": "AOG排故属于典型的矩阵式项目管理，授权跨部门调配资源旨在解决“各自为战”的弊端，缩短沟通链条，核心目标是提升响应速度。考点速记：项目管理中的“授权”对应权责对等与扁平化指挥。"
  },
  {
    "id": "管理学_1780641191317_2_uofi",
    "module": "管理学",
    "stem": "在C检现场，一名已连续工作9小时的机务人员因极度疲劳，在执行发动机磁堵检查时严重走神，险些漏检金属屑末。车间主任发现后强制其休息并调整排班。从“人本管理”与“安全管理体系”双重角度看，车间主任的做法符合：",
    "options": [
      {
        "label": "A",
        "text": "X理论，认为工人天生懒惰需要强制管控"
      },
      {
        "label": "B",
        "text": "Y理论及机务疲劳管理要求，关注员工生理状态对安全的影响"
      },
      {
        "label": "C",
        "text": "超Y理论，强调因人而异的权变管理"
      },
      {
        "label": "D",
        "text": "目标管理，通过惩罚杜绝人员思想麻痹"
      }
    ],
    "answer": "B",
    "explanation": "Y理论假设人愿意承担责任，但疲劳会导致不可控的差错。强制休息体现了对“人为因素”中疲劳维度的科学控制，符合局方和航企的疲劳管理制度。考点速记：Y理论主张创造良好环境释放潜力，安全管理底线不能触碰。"
  },
  {
    "id": "管理学_1780641191317_3_j5hv",
    "module": "管理学",
    "stem": "某机务班组在进行A320定检封胶作业时，教员老王对新员工说：“打胶不只是把缝糊上，你要判断如果这里积水结冰，胶层老化后是否会导致结构腐蚀。”老王的教导属于管理中的：",
    "options": [
      {
        "label": "A",
        "text": "技术授权，告诉员工怎么干"
      },
      {
        "label": "B",
        "text": "愿景灌输，提升员工职业使命感"
      },
      {
        "label": "C",
        "text": "内隐知识传递与情景意识培养，提升决策质量"
      },
      {
        "label": "D",
        "text": "理论说教，弥补基础培训的缺失"
      }
    ],
    "answer": "C",
    "explanation": "经验丰富的师傅传递的是基于情境的判断力（即“Know-how”），这属于内隐知识，有助于提升员工对风险的情景意识（Situation Awareness）。考点速记：内隐知识难以文字化，辅导是传递隐性知识的主要途径。"
  },
  {
    "id": "管理学_1780641191317_4_hhrh",
    "module": "管理学",
    "stem": "在A330发动机换发项目中，项目经理制定了详细的甘特图。执行过程中，液压管路连接因等待特殊封圈延误了2天，但项目经理并未立即调整后续QEC（发动机快速换装组件）组装计划，依然按原节点执行，结果导致总装时工序冲突彻底停工。从管理学角度分析，项目经理主要违背了：",
    "options": [
      {
        "label": "A",
        "text": "统一指挥原则，多头领导导致混乱"
      },
      {
        "label": "B",
        "text": "权变管理理论，未根据环境变化调整方案"
      },
      {
        "label": "C",
        "text": "反馈控制原理与动态适应原则，忽视滞后工序的联动调整"
      },
      {
        "label": "D",
        "text": "效率优先原则，过分追求速度而忽视成本"
      }
    ],
    "answer": "C",
    "explanation": "关键路径上的延误必须立刻分析对后续紧后工序的影响并调整计划。项目经理发现问题却未做动态调整，属于计划控制的严重僵化。考点速记：计划应是滚动（动态）的，关键路径延误需立即进行工期优化。"
  },
  {
    "id": "管理学_1780641191317_5_xeyo",
    "module": "管理学",
    "stem": "在波音787定检排故中，电子舱气味异常，放行人员老赵按照简图页排故无果。此时距航班起飞仅剩3小时，老赵未上报值班经理，也未启动技术支援，而是凭经验继续深挖，最终导致航班恶性延误。老赵的领导风格在管理方格理论中最接近于：",
    "options": [
      {
        "label": "A",
        "text": "贫乏型管理(1,1)，对人与工作都不关心"
      },
      {
        "label": "B",
        "text": "乡村俱乐部型管理(1,9)，过分注重人情关系"
      },
      {
        "label": "C",
        "text": "任务型管理(9,1)，极高任务导向但极度缺乏协作沟通"
      },
      {
        "label": "D",
        "text": "中庸之道型管理(5,5)，平衡各方利益"
      }
    ],
    "answer": "C",
    "explanation": "老赵“单打独斗”表现出了极高的排故意愿（高任务导向），但忽视了组织资源、技术支持与信息通报（低协作），属于典型的9,1任务型管理。考点速记：(9,1)型管理者重作业而轻关系，容易破坏系统协同。"
  },
  {
    "id": "管理学_1780641191317_6_os4m",
    "module": "管理学",
    "stem": "维修基地推行“精益维修”管理，要求将定检中的高架车、航材、工具车进行“定置定位”并绘制行走路线图，消除不必要的走动和搬运。精益管理的这一举措核心在于消除：",
    "options": [
      {
        "label": "A",
        "text": "过度维修造成的安全冗余"
      },
      {
        "label": "B",
        "text": "动作浪费与运输浪费，提升流动作业效率"
      },
      {
        "label": "C",
        "text": "组织架构的层级浪费，实行扁平化"
      },
      {
        "label": "D",
        "text": "多余的生产计划，实现零库存"
      }
    ],
    "answer": "B",
    "explanation": "定置定位和优化动线直接针对精益七大浪费中的“动作浪费”和“搬运浪费”，在机务维修中这直接减少了接送工具的时间，提高了有效工时。考点速记：精益七大浪费——搬运、库存、动作、等待、过量生产、多余工序、缺陷。"
  },
  {
    "id": "管理学_1780641191317_7_qz7z",
    "module": "管理学",
    "stem": "空客A350定检组在试车环节发生漏油，组长立即叫停。随后，组长与质量、技术、试车员围在一起采用“头脑风暴法”分析漏点。组长要求“不准批评任何人的看法，哪怕是看似荒谬的猜测”。这遵循了头脑风暴法的哪项原则？",
    "options": [
      {
        "label": "A",
        "text": "聚焦原则，集中讨论漏油问题"
      },
      {
        "label": "B",
        "text": "延迟评判原则，以营造心理安全氛围激发想象力"
      },
      {
        "label": "C",
        "text": "权威导向原则，由技术权威最后拍板"
      },
      {
        "label": "D",
        "text": "记录复盘原则，侧重记录而非思考"
      }
    ],
    "answer": "B",
    "explanation": "头脑风暴法最核心的规则就是“庭外判决”原则（延迟评判），禁止在畅谈阶段批评，否则会扼杀创意，导致技术骨干不敢提出非常规故障原因。考点速记：头脑风暴——自由奔放、延迟评判、以量求质、结合改善。"
  },
  {
    "id": "管理学_1780641191317_8_impm",
    "module": "管理学",
    "stem": "机务班组实行“工时奖金包干”改革，将原来按级别发固定奖金改为按完成定检工卡的实际工时结算，并且引入了工卡难度系数。实行后第一个月，发现有个别员工为了提高工时，简化了推梯子、系安全带等安全防护步骤。这体现了管理控制中的：",
    "options": [
      {
        "label": "A",
        "text": "控制标准过于模糊导致的随意性"
      },
      {
        "label": "B",
        "text": "掉入“陷阱”，即量化考核导致目标置换，忽视安全禁区"
      },
      {
        "label": "C",
        "text": "人性假设错误，员工普遍性恶"
      },
      {
        "label": "D",
        "text": "破窗效应，个别违规引发集体违规"
      }
    ],
    "answer": "B",
    "explanation": "目标置换是指在考核中，被考核者过分关注可量化的指标（工时）而忽略了不可妥协的核心目标（安全合规）。安全防护步骤是刚性底线，绝不能因追求效率而被“置换”。考点速记：管理考核需平衡量化指标与底线指标。"
  },
  {
    "id": "管理学_1780641191317_9_6ptb",
    "module": "管理学",
    "stem": "某工程技术公司同时执行3架飞机的C检和2路外站排故。生产经理老何不仅关心各组任务进度，还特别关注夜班员工的身体保暖和食堂夜宵质量。根据俄亥俄州立大学领导行为理论，老何的双重关注属于：",
    "options": [
      {
        "label": "A",
        "text": "非此即彼的矛盾行为"
      },
      {
        "label": "B",
        "text": "高关怀维度与高定规维度的双重强领导"
      },
      {
        "label": "C",
        "text": "英雄主义领导风格"
      },
      {
        "label": "D",
        "text": "交易型领导，用夜宵换取加班"
      }
    ],
    "answer": "B",
    "explanation": "俄亥俄州立大学理论将领导行为分为“关怀维度”（关心人，如夜宵保障）和“定规维度”（关心任务，如推进C检进度）。老何两方面都抓，属于“高一高”型领导。考点速记：领导行为双维度——体贴（关怀）与主动结构（定规）。"
  },
  {
    "id": "管理学_1780641191317_10_8p6y",
    "module": "管理学",
    "stem": "某航司推行APS（Arrangement安排、Preparation准备、Sequence施工）机务管理理念。在B737MAX定检中，班组长编制“关键工序风险鱼骨图”，并预先准备好对应排故的专用工具。这最契合APS理论中的哪个环节？",
    "options": [
      {
        "label": "A",
        "text": "生产保障（Logistics），仅仅为了工具不丢失"
      },
      {
        "label": "B",
        "text": "准备（Preparation），即识别风险、进行资源准备与桌面推演"
      },
      {
        "label": "C",
        "text": "施工（Sequence），直接执行标准化作业"
      },
      {
        "label": "D",
        "text": "反馈（Feedback），总结排故经验"
      }
    ],
    "answer": "B",
    "explanation": "APS理论中，“安排”侧重于计划分工，“准备”侧重于风险识别、物料工具验证和预案制定，“施工”侧重于执行。绘制鱼骨图分析风险并准备专用工具属于典型的准备阶段。考点速记：APS——凡事有安排，凡事有准备，凡事按标准。"
  },
  {
    "id": "管理学_1780641191317_11_p3ug",
    "module": "管理学",
    "stem": "班组晨会上，技术骨干大刘直接当着全班的面指责班组长：“你的排班表安排小张做发动机孔探就是个错误，他才拿证，根本没独立做过。”若你作为班组长，根据“建设性冲突”的处理原则，最合理的反应是：",
    "options": [
      {
        "label": "A",
        "text": "严厉警告大刘扰乱会议纪律，会后私下讨论"
      },
      {
        "label": "B",
        "text": "无视质疑，因为班组长有绝对权威，无需解释"
      },
      {
        "label": "C",
        "text": "认可大刘对安全的严谨态度，引导大家针对‘如何做好带教技能传承’展开讨论"
      },
      {
        "label": "D",
        "text": "立刻修改排班表，撤销小张本次工作以避免冲突"
      }
    ],
    "answer": "C",
    "explanation": "建设性冲突有利于暴露安全风险。班组长应将针对“人的攻击”转化为针对“事（任务分配合理性、带教机制）”的讨论，既不压制声音又导向解决问题。考点速记：应对冲突——接纳情绪，聚焦问题，结构化解决。"
  },
  {
    "id": "管理学_1780641191317_12_vxhw",
    "module": "管理学",
    "stem": "一架A319执行A检，涉及发动机滑油更换与气象雷达测试。班组长把组员分成两组，一组负责发动机工作（甲），一组负责电子测试（乙），并指定一名副班组长专门协调两组之间的牵引车使用时间，避免互相等待。这种分组属于：",
    "options": [
      {
        "label": "A",
        "text": "按职能划分的业务小组"
      },
      {
        "label": "B",
        "text": "流程型组织，按时间轴分配"
      },
      {
        "label": "C",
        "text": "矩阵式管理，完全打破职能"
      },
      {
        "label": "D",
        "text": "并行工程与联络机制，通过协调者解决物理资源冲突"
      }
    ],
    "answer": "D",
    "explanation": "两组同时作业属于并行工程；专门指派副班组长解决牵引车冲突，是设立了专门的“联络官”角色来处理界面资源冲突，属于项目管理中的资源平衡。考点速记：并行作业需配备解决资源冲突的协调机制。"
  },
  {
    "id": "管理学_1780641191317_13_41dp",
    "module": "管理学",
    "stem": "在V2500发动机孔探检查中，发现高压涡轮叶片有一处烧蚀坑。助理工程师认为应按手册标准判定报废，而带教的技术工程师则认为这种烧蚀在旧型号中很常见，可以通过打磨修复。面对冲突，班组长的决策应符合“循证决策”的是：",
    "options": [
      {
        "label": "A",
        "text": "尊重老技术员的经验，经验是机务的灵魂"
      },
      {
        "label": "B",
        "text": "选择最保守的做法报废，以求绝对安全"
      },
      {
        "label": "C",
        "text": "暂停争论，立即依据当前有效版AMM/SB手册中的损伤容限标准进行测量后再决策"
      },
      {
        "label": "D",
        "text": "为了节约航材成本，采纳打磨修复的建议"
      }
    ],
    "answer": "C",
    "explanation": "循证决策（Evidence-Based Management）强调依据最佳的客观证据，而非单纯的资历、直觉或成本来决策。手册标准是最具法律效力和科学性的证据。考点速记：权威来源于手册标准，而非职务高低。"
  },
  {
    "id": "管理学_1780641191317_14_n5cj",
    "module": "管理学",
    "stem": "双发宽体机B777右发FOD（外来物损伤）进气道排故。机务项目经理绘制了网络图：A（拆卸）=4h，B（探伤）=2h，C（修复）=6h，D（回装测试）=3h，且A必须完成后B和C才能开始，B和C都完成才能开始D。该项目的理论最短工期是多少小时？",
    "options": [
      {
        "label": "A",
        "text": "15小时"
      },
      {
        "label": "B",
        "text": "13小时"
      },
      {
        "label": "C",
        "text": "12小时"
      },
      {
        "label": "D",
        "text": "17小时"
      }
    ],
    "answer": "B",
    "explanation": "关键路径分析：路径1：A+B+D=4+2+3=9h；路径2：A+C+D=4+6+3=13h。关键路径是耗时最长的路径，决定了项目总工期，故为13小时。考点速记：关键路径是网络图中耗时最长的逻辑路径，无浮动时间。"
  },
  {
    "id": "管理学_1780641191317_15_5kh3",
    "module": "管理学",
    "stem": "某基地对所有C检工卡开展“防错验证”管理（俗称防呆法）。在安装A320主轮时，设计了一个专用套筒，只有使用该套筒才能达到规定力矩，且套筒连在力矩扳手上不会装反。这属于防呆法中的：",
    "options": [
      {
        "label": "A",
        "text": "警告提示原则，亮红灯提醒"
      },
      {
        "label": "B",
        "text": "缓和影响原则，降低事故后果"
      },
      {
        "label": "C",
        "text": "断根原理与保险原理，通过物理结构消除错误发生的可能"
      },
      {
        "label": "D",
        "text": "层别管理原则，区分合格与不合格"
      }
    ],
    "answer": "C",
    "explanation": "防呆法的最高境界是“断根”，即利用物理结构设计让错误不可能发生。专用套筒不仅无法装反，还能锁定力矩，从物理上消除了错装和力矩不足的可能。考点速记：防错十大原理——断根、保险、自动、相符、顺序、隔离、复制、层别、警告、缓和。"
  },
  {
    "id": "管理学_1780641191317_16_4flq",
    "module": "管理学",
    "stem": "机务带班组长小陈因工作任务繁重，经常直接在微信群里用一大段长语音下达排故指令。结果多次出现组员漏听关键步骤导致出错。小陈的问题主要违背了沟通管理中的：",
    "options": [
      {
        "label": "A",
        "text": "非正式沟通网络的优势"
      },
      {
        "label": "B",
        "text": "编码准确性与媒介适应性，复杂指令未采用文字工卡确认"
      },
      {
        "label": "C",
        "text": "情感激励法则，缺乏人文关怀"
      },
      {
        "label": "D",
        "text": "链式沟通的准确性"
      }
    ],
    "answer": "B",
    "explanation": "复杂的技术指令（如排故步骤）需要可留存、可回溯、信息稳定度高的媒介（如文字工卡或图文交接单）。长语音属于高噪音、低留存的媒介，极易造成解码偏差。考点速记：沟通媒介选择——复杂信息需标准化、可视化。"
  },
  {
    "id": "管理学_1780641191317_17_ij8x",
    "module": "管理学",
    "stem": "某架A330空调组件流量故障，排故周期原本计划3天。项目负责人评估后认为，如果直接更换整个热交换器组件（成本高），只需要1天即可出厂；如果深度修理散热器（成本低），需要5天。负责人考虑到正值暑运，停场损失每天高达数十万元，果断选用直接更换方案。这体现了：",
    "options": [
      {
        "label": "A",
        "text": "价值工程与成本效益分析，综合考虑直接航材和间接停场成本"
      },
      {
        "label": "B",
        "text": "这是明显的浪费，应始终选择维修而非更换"
      },
      {
        "label": "C",
        "text": "急功近利，只顾生产不顾成本"
      },
      {
        "label": "D",
        "text": "风险规避，为了省事忽略深度修理"
      }
    ],
    "answer": "A",
    "explanation": "管理决策需要在全生命周期成本中考量。直接更换虽然航材贵，但节省了巨大的机会成本（停场损失）。这是基于总拥有成本（TCO）的价值分析决策。考点速记：维修决策需平衡直接成本与间接损失。"
  },
  {
    "id": "管理学_1780641191317_18_h3fp",
    "module": "管理学",
    "stem": "发动机试车台管理班组内，老张和老王因排班时长不均发生激烈争吵。班组长小李没有评价谁对谁错，而是把班组的排班规则拿出来，对着工时记录表重新核对了最后一季度的所有工时，发现工具间值班漏记工时导致了不均。小李据此解决了问题。小李的管理风格属于：",
    "options": [
      {
        "label": "A",
        "text": "感性的乡村俱乐部式氛围管理"
      },
      {
        "label": "B",
        "text": "法制化（规则导向）管理，依靠透明制度与数据裁定冲突"
      },
      {
        "label": "C",
        "text": "放任式管理，谁嗓门大听谁的"
      },
      {
        "label": "D",
        "text": "个人英雄主义，强行压制冲突"
      }
    ],
    "answer": "B",
    "explanation": "面对人际冲突，高明的管理者不通过“和稀泥”解决，而是通过回归制度（排班规则）和数据（工时记录）来判断。这确立了规则的刚性，消除了员工的相对剥夺感。考点速记：制度管人、流程管事、数据说话。"
  },
  {
    "id": "管理学_1780641191317_19_ykgh",
    "module": "管理学",
    "stem": "在执行发动机水洗勤务时，班组长发现组员小赵未穿戴护目镜。小赵反驳说：“这个项目清洗剂无毒，手册也没写必须戴，我觉得没必要。”班组长演示了如果微量液体不慎溅入眼睛，将导致停工洗消及眼角膜损伤。班组长履行的是管理职能中的：",
    "options": [
      {
        "label": "A",
        "text": "指挥调度，下令必须穿戴"
      },
      {
        "label": "B",
        "text": "现场教练（辅导）职能，通过逻辑推演改变认知误区并展示后果"
      },
      {
        "label": "C",
        "text": "行政奖惩，不戴就罚款"
      },
      {
        "label": "D",
        "text": "监督检查，发现隐患"
      }
    ],
    "answer": "B",
    "explanation": "班组长不仅指出了问题，还通过逻辑推演展示了后果，这改变了员工的认知（从“有没有毒”上升到“物理损伤”），属于深层次的辅导与教育职能，体现了对员工健康的负责。考点速记：管理者不仅要“管”，更要“理”（讲道理、理情绪）。"
  }
]